LICENSE
MANIFEST.in
README.md
setup.py
arcgis/__init__.py
arcgis/arcgis.py
arcgis_rest_query.egg-info/PKG-INFO
arcgis_rest_query.egg-info/SOURCES.txt
arcgis_rest_query.egg-info/dependency_links.txt
arcgis_rest_query.egg-info/requires.txt
arcgis_rest_query.egg-info/top_level.txt
bin/arcgis-get