Metadata-Version: 1.0
Name: arcgis-rest-query
Version: 0.12
Summary: A tool to download a layer from an ArcGIS web service as GeoJSON
Home-page: https://github.com/Schwanksta/python-arcgis-rest-query
Author: Ken Schwencke
Author-email: schwank@gmail.com
License: MIT
Platform: UNKNOWN
